<?xml version="1.0" encoding="UTF-8"?>
<office:document-meta xmlns:office="urn:oasis:names:tc:opendocument:xmlns:office:1.0" xmlns:xlink="http://www.w3.org/1999/xlink" xmlns:dc="http://purl.org/dc/elements/1.1/" xmlns:meta="urn:oasis:names:tc:opendocument:xmlns:meta:1.0" xmlns:ooo="http://openoffice.org/2004/office" xmlns:grddl="http://www.w3.org/2003/g/data-view#" office:version="1.2"><office:meta><meta:generator>LibreOffice/6.0.7.3$Linux_X86_64 LibreOffice_project/00m0$Build-3</meta:generator><meta:initial-creator>Daniela Mattos</meta:initial-creator><meta:creation-date>2015-10-15T15:56:00Z</meta:creation-date><dc:date>2019-09-05T13:55:16.335392246</dc:date><meta:print-date>2017-02-24T16:35:00Z</meta:print-date><meta:editing-cycles>100</meta:editing-cycles><meta:editing-duration>PT17H25M3S</meta:editing-duration><meta:document-statistic meta:table-count="2" meta:image-count="1" meta:object-count="0" meta:page-count="2" meta:paragraph-count="76" meta:word-count="308" meta:character-count="2226" meta:non-whitespace-character-count="1894"/><meta:template xlink:type="simple" xlink:actuate="onRequest" xlink:title="" xlink:href="../FORM.AP.001%20-%20Formulário%20Apoio%20Requisição%20de%20Viagem%20-%20Felipe%20-%2004-10.odt/Normal"/></office:meta></office:document-meta>